LICENSE.md
MANIFEST.in
README.md
pyproject.toml
setup.py
src/fouroversix/__init__.py
src/fouroversix/backend.py
src/fouroversix/frontend.py
src/fouroversix/ops.py
src/fouroversix/utils.py
src/fouroversix.egg-info/PKG-INFO
src/fouroversix.egg-info/SOURCES.txt
src/fouroversix.egg-info/dependency_links.txt
src/fouroversix.egg-info/requires.txt
src/fouroversix.egg-info/top_level.txt
src/fouroversix/csrc/bindings.cpp
src/fouroversix/csrc/fp4_gemm.cu
src/fouroversix/csrc/fp4_gemm_sm120.cu
src/fouroversix/csrc/include/element_traits.hpp
src/fouroversix/csrc/include/fp4_quant.h
src/fouroversix/csrc/include/fp4_quant_kernel.h
src/fouroversix/csrc/include/fp4_quant_launch_template.h
src/fouroversix/csrc/include/hardware_info.h
src/fouroversix/csrc/include/kernel_traits.h
src/fouroversix/csrc/include/static_switch.h
src/fouroversix/csrc/include/utils.h
src/fouroversix/csrc/quantize/fp4_quant.cu
src/fouroversix/csrc/quantize/fp4_quant_bf16_mxfp4_rht_sm100.cu
src/fouroversix/csrc/quantize/fp4_quant_bf16_mxfp4_rht_trans_sm100.cu
src/fouroversix/csrc/quantize/fp4_quant_bf16_mxfp4_sm100.cu
src/fouroversix/csrc/quantize/fp4_quant_bf16_mxfp4_trans_sm100.cu
src/fouroversix/csrc/quantize/fp4_quant_bf16_nvfp4_rht_sm100.cu
src/fouroversix/csrc/quantize/fp4_quant_bf16_nvfp4_rht_trans_sm100.cu
src/fouroversix/csrc/quantize/fp4_quant_bf16_nvfp4_sm100.cu
src/fouroversix/csrc/quantize/fp4_quant_bf16_nvfp4_trans_sm100.cu
src/fouroversix/csrc/quantize/fp4_quant_fp16_mxfp4_rht_sm100.cu
src/fouroversix/csrc/quantize/fp4_quant_fp16_mxfp4_rht_trans_sm100.cu
src/fouroversix/csrc/quantize/fp4_quant_fp16_mxfp4_sm100.cu
src/fouroversix/csrc/quantize/fp4_quant_fp16_mxfp4_trans_sm100.cu
src/fouroversix/csrc/quantize/fp4_quant_fp16_nvfp4_rht_sm100.cu
src/fouroversix/csrc/quantize/fp4_quant_fp16_nvfp4_rht_trans_sm100.cu
src/fouroversix/csrc/quantize/fp4_quant_fp16_nvfp4_sm100.cu
src/fouroversix/csrc/quantize/fp4_quant_fp16_nvfp4_trans_sm100.cu
src/fouroversix/model/__init__.py
src/fouroversix/model/fp4_linear.py
src/fouroversix/model/quantize.py
src/fouroversix/quantize/__init__.py
src/fouroversix/quantize/fp4_tensor.py
src/fouroversix/quantize/reference.py
src/fouroversix/quantize/rht_utils.py
