Metadata-Version: 2.4
Name: fouroversix
Version: 0.3.0
Summary: More Accurate FP4 Quantization with Adaptive Block Scaling
Author-email: Jack Cook <cookj@mit.edu>, Junxian Guo <junxian@mit.edu>
License-Expression: MIT
Requires-Python: >=3.10
License-File: LICENSE.md
Requires-Dist: torch~=2.9.1
Provides-Extra: docs
Requires-Dist: mkdocs~=1.6.1; extra == "docs"
Requires-Dist: mkdocs-material~=9.7.1; extra == "docs"
Requires-Dist: mkdocstrings[python]~=1.0.1; extra == "docs"
Provides-Extra: tests
Requires-Dist: lm_eval[hf]~=0.4.10; extra == "tests"
Requires-Dist: modal~=1.3.1; extra == "tests"
Requires-Dist: pytest~=8.1.1; extra == "tests"
Requires-Dist: ruff~=0.14.14; extra == "tests"
Requires-Dist: SQLAlchemy~=2.0.46; extra == "tests"
Dynamic: license-file
